setup.py
pikopy/__init__.py
pikopy/piko.py
pikopy.egg-info/PKG-INFO
pikopy.egg-info/SOURCES.txt
pikopy.egg-info/dependency_links.txt
pikopy.egg-info/requires.txt
pikopy.egg-info/top_level.txt
pikopy/submodule/__init__.py
tests/__init__.py
tests/test_piko.py