Metadata-Version: 1.1
Name: pikopy
Version: 0.9.0
Summary: A package for working with a Piko Inverter from Kostal
Home-page: https://github.com/Tafkas/KostalPikoPy
Author: Christian Stade-Schuldt
Author-email: stadeschuldt@gmail.com
License: GPL
Download-URL: https://github.com/Tafkas/KostalPikoPy
Keywords: python kostal piko inverter photovoltaic solar
Platform: UNKNOWN
Classifier: Development Status :: 5 - Production/Stable
Classifier: Natural Language :: English
Classifier: Operating System :: OS Independent
Classifier: Programming Language :: Python :: 2
Classifier: License :: OSI Approved :: MIT License
Classifier: Topic :: Internet
Classifier: Topic :: Internet :: WWW/HTTP
